tap_userflow/__init__.py
tap_userflow/client.py
tap_userflow/schemas/attribute_definitions.schema.json
tap_userflow/schemas/content.schema.json
tap_userflow/schemas/content_sessions.schema.json
tap_userflow/schemas/content_versions.schema.json
tap_userflow/schemas/event_definitions.schema.json
tap_userflow/schemas/groups.schema.json
tap_userflow/schemas/users.schema.json
tap_userflow/streams.py
tap_userflow/tap.py
kingalban_tap_userflow-1.2.1.dist-info/LICENSE
kingalban_tap_userflow-1.2.1.dist-info/METADATA
kingalban_tap_userflow-1.2.1.dist-info/WHEEL
kingalban_tap_userflow-1.2.1.dist-info/entry_points.txt
kingalban_tap_userflow-1.2.1.dist-info/RECORD
