Metadata-Version: 2.1
Name: kingalban-tap-userflow
Version: 1.2.1
Summary: `tap-userflow` is a Singer tap for UserFlow, built with the Meltano Singer SDK.
License: Apache-2.0
Keywords: ELT,UserFlow
Author: Alban King
Author-email: kingalban@gmail.com
Requires-Python: >=3.8,<4
Classifier: License :: OSI Approved :: Apache Software License
Classifier: Programming Language :: Python :: 3
Classifier: Programming Language :: Python :: 3.8
Classifier: Programming Language :: Python :: 3.9
Classifier: Programming Language :: Python :: 3.10
Classifier: Programming Language :: Python :: 3.11
Classifier: Programming Language :: Python :: 3.12
Provides-Extra: s3
Requires-Dist: fs-s3fs (>=1.1.1,<1.2.0) ; extra == "s3"
Requires-Dist: requests (>=2.31.0,<2.32.0)
Requires-Dist: singer-sdk (>=0.34.1,<0.35.0)
